varana/__init__.py
varana/detrend.py
varana/fit.py
varana/freq_comb.py
varana/phase.py
varana/plt_pdgrm.py
varana/trim.py
varana-1.1.0.data/scripts/detrend.py
varana-1.1.0.data/scripts/fit.py
varana-1.1.0.data/scripts/freq_comb.py
varana-1.1.0.data/scripts/phase.py
varana-1.1.0.data/scripts/plt_pdgrm.py
varana-1.1.0.data/scripts/trim.py
varana-1.1.0.dist-info/LICENSE
varana-1.1.0.dist-info/METADATA
varana-1.1.0.dist-info/WHEEL
varana-1.1.0.dist-info/top_level.txt
varana-1.1.0.dist-info/RECORD
