Metadata-Version: 2.1
Name: varana
Version: 1.1.0
Summary: Analyse the variability of stars
Home-page: https://github.com/pbrus/variability-analyser/tree/master/varana
Author: Przemysław Bruś
License: UNKNOWN
Keywords: variability,time,series,stars,magnitude
Platform: UNKNOWN
Classifier: Development Status :: 5 - Production/Stable
Classifier: Intended Audience :: Science/Research
Classifier: License :: OSI Approved :: MIT License
Classifier: Operating System :: OS Independent
Classifier: Programming Language :: Python
Classifier: Programming Language :: Python :: 3.6
Classifier: Programming Language :: Python :: 3.7
Classifier: Programming Language :: Python :: 3.8
Classifier: Topic :: Scientific/Engineering :: Astronomy
Classifier: Topic :: Utilities
Requires-Python: >=3.6
Requires-Dist: astropy (>=4.1)
Requires-Dist: matplotlib (>=3.3.4)
Requires-Dist: numpy (>=1.19.5)
Requires-Dist: scipy (>=1.5.4)
